eventify/__init__.py
eventify/base_handler.py
eventify/service.py
eventify/util.py
eventify/drivers/__init__.py
eventify/drivers/base.py
eventify/drivers/crossbar.py
eventify/drivers/kafka.py
eventify/drivers/zeromq.py
eventify/event/__init__.py
eventify/exceptions/__init__.py
eventify/persist/__init__.py
eventify/persist/constants.py
eventify/tracking/__init__.py
eventify/tracking/constants.py
eventify-0.5.25.dist-info/LICENSE
eventify-0.5.25.dist-info/METADATA
eventify-0.5.25.dist-info/WHEEL
eventify-0.5.25.dist-info/top_level.txt
eventify-0.5.25.dist-info/RECORD
